<?xml version="1.0" ?>
<updates>
	<update>
		<name>wbc_blanco_j4</name>
		<description>WBC_Blanco J4/J5/J6 Template - Update</description>
		<element>wbc_blanco_j4</element>
		<type>template</type>
		<client>site</client>
		<version>2.0.19</version>
		<infourl title="wbc_blaco_j4 Template">https://github.com/coweb01/wbc_blanco_j4</infourl>
		<downloads>
			<downloadurl type="full" format="zip">https://github.com/coweb01/wbc_blanco_j4/releases/download/2.0.19/wbc_blanco_j4-2.0.19.zip</downloadurl>
		</downloads>
		<tags>stable</tags>
		<sha512>3de6d7914dbce29895d3fea1d33bf13f758f132c80762b4400c7839b1a1ead2fdab205d0d478e99ee47efebd748a9154eb868e55a354f4871d31c0fdafdde94c</sha512>
		<maintainer>Claudia Oerter</maintainer>
		<maintainerurl>https://www.das-webconcept.de</maintainerurl>
		<php_minimum>7.2.5</php_minimum>
		<targetplatform name="joomla" version="5.[1234567890]"/>
	</update>
</updates>
